Metadata-Version: 2.1
Name: pyspypoint
Version: 1.0.2
Summary: Client for SPYPOINT
Home-page: https://github.com/hstern/pyspypoint
Author: Henry Stern
Author-email: henry@stern.ca
License: Apache 2.0
Platform: UNKNOWN
Classifier: Development Status :: 5 - Production/Stable
Classifier: License :: OSI Approved :: Apache Software License
Classifier: Programming Language :: Python :: 3
Classifier: Programming Language :: Python :: 3.6
Classifier: Programming Language :: Python :: 3.7
Classifier: Programming Language :: Python :: 3.8
Classifier: Programming Language :: Python :: 3.9
Provides-Extra: test
